xbkit/__init__.py
xbkit/bot/__init__.py
xbkit/bot/ncatbot.py
xbkit/browser/__init__.py
xbkit/browser/client.py
xbkit/cli/__init__.py
xbkit/cli/parser.py
xbkit/match/__init__.py
xbkit/match/rule.py
xbkit-0.1.2.dist-info/licenses/LICENSE-APACHE
xbkit-0.1.2.dist-info/licenses/LICENSE-MIT
xbkit-0.1.2.dist-info/METADATA
xbkit-0.1.2.dist-info/WHEEL
xbkit-0.1.2.dist-info/top_level.txt
xbkit-0.1.2.dist-info/RECORD
