Metadata-Version: 2.4
Name: xbkit
Version: 0.1.2
Summary: 小白开发工具包,仅便于自己学习交流使用,不保证接口的稳定性,请谨慎使用!!!
Author-email: xb1520 <xb1520@foxmail.com>
License-Expression: MIT OR Apache-2.0
Project-URL: Homepage, https://github.com/xb1520/xbkit
Project-URL: Issues, https://github.com/xb1520/xbkit/issues
Requires-Python: >=3.13
License-File: LICENSE-MIT
License-File: LICENSE-APACHE
Provides-Extra: bot
Requires-Dist: ncatbot==3.8.9.post1; extra == "bot"
Provides-Extra: browser
Requires-Dist: playwright>=1.54.0; extra == "browser"
Requires-Dist: playwright-stealth>=2.0.0; extra == "browser"
Dynamic: license-file
